AUTHORS
HISTORY.rst
LICENSE
MANIFEST.in
README.rst
setup.cfg
setup.py
django_wysiwyg_redactor_ng.egg-info/PKG-INFO
django_wysiwyg_redactor_ng.egg-info/SOURCES.txt
django_wysiwyg_redactor_ng.egg-info/dependency_links.txt
django_wysiwyg_redactor_ng.egg-info/not-zip-safe
django_wysiwyg_redactor_ng.egg-info/requires.txt
django_wysiwyg_redactor_ng.egg-info/top_level.txt
redactor/__init__.py
redactor/fields.py
redactor/forms.py
redactor/handlers.py
redactor/urls.py
redactor/utils.py
redactor/views.py
redactor/widgets.py
redactor/static/redactor/django_admin.css
redactor/static/redactor/jquery.redactor.init.js
redactor/static/redactor/redactor.css
redactor/static/redactor/redactor.js
redactor/static/redactor/redactor.min.css
redactor/static/redactor/redactor.min.js
redactor/static/redactor/_scss/_content.scss
redactor/static/redactor/_scss/_dropdown.scss
redactor/static/redactor/_scss/_icons.scss
redactor/static/redactor/_scss/_mixins.scss
redactor/static/redactor/_scss/_modal.scss
redactor/static/redactor/_scss/_ui.scss
redactor/static/redactor/_scss/_variables.scss
redactor/static/redactor/_scss/redactor.scss
redactor/static/redactor/css/django_admin.css
redactor/static/redactor/css/docstyle.css
redactor/static/redactor/css/redactor.css
redactor/static/redactor/css/redactor.less
redactor/static/redactor/css/style.css
redactor/static/redactor/css/wym.css
redactor/static/redactor/img/icons.png
redactor/static/redactor/langs/ar.js
redactor/static/redactor/langs/az.js
redactor/static/redactor/langs/ba.js
redactor/static/redactor/langs/bg.js
redactor/static/redactor/langs/by.js
redactor/static/redactor/langs/ca.js
redactor/static/redactor/langs/cs.js
redactor/static/redactor/langs/da.js
redactor/static/redactor/langs/de.js
redactor/static/redactor/langs/el.js
redactor/static/redactor/langs/en.js
redactor/static/redactor/langs/eo.js
redactor/static/redactor/langs/es.js
redactor/static/redactor/langs/es_ar.js
redactor/static/redactor/langs/fa.js
redactor/static/redactor/langs/fi.js
redactor/static/redactor/langs/fr.js
redactor/static/redactor/langs/ge.js
redactor/static/redactor/langs/he.js
redactor/static/redactor/langs/hr.js
redactor/static/redactor/langs/hu.js
redactor/static/redactor/langs/id.js
redactor/static/redactor/langs/it.js
